{
  "symbol": "宫位卦爻关系",
  "category": "guayao",
  "core_properties": [
    "本宫/他宫",
    "内外",
    "世应",
    "飞伏"
  ],
  "rules": {
    "本宫卦": {
      "象": [
        "纯正",
        "核心",
        "本家",
        "无外来干扰",
        "事情纯粹"
      ]
    },
    "一世卦": {
      "象": [
        "第一爻变成另一宫",
        "事情刚开始就变味",
        "根基动摇"
      ]
    },
    "二世卦": {
      "象": [
        "第二爻变",
        "内部开始变化",
        "中层出问题"
      ]
    },
    "三世卦": {
      "象": [
        "第三爻变",
        "变化到中间",
        "事情发展中转折"
      ]
    },
    "四世卦": {
      "象": [
        "第四爻变",
        "外部变化",
        "上面出问题"
      ]
    },
    "五世卦": {
      "象": [
        "第五爻变",
        "高位动摇",
        "快到头了"
      ]
    },
    "游魂卦": {
      "象": [
        "漂泊不定",
        "在外游荡",
        "心不在此",
        "无根"
      ]
    },
    "归魂卦": {
      "象": [
        "回归",
        "回家",
        "事情收尾",
        "落叶归根"
      ]
    }
  },
  "shiying": {
    "世爻": {
      "象": [
        "自己",
        "我方",
        "问事主体",
        "当前状态",
        "核心关切"
      ]
    },
    "应爻": {
      "象": [
        "对方",
        "环境",
        "所问之事",
        "外部因素",
        "未来走向"
      ]
    }
  },
  "feifu": {
    "飞神": {
      "象": [
        "表面显现的",
        "挂在上面的",
        "可见的"
      ]
    },
    "伏神": {
      "象": [
        "隐藏的",
        "不露面的",
        "潜在的(可能是机会也可能是隐患)"
      ]
    }
  },
  "contexts": {
    "career": {
      "世爻": [
        "自己的工作/状态"
      ],
      "游魂": [
        "漂泊不定/想跳槽"
      ],
      "归魂": [
        "想回老东家/该稳定了"
      ]
    }
  }
}