{
  "symbol": "三刑",
  "category": "guayao",
  "core_properties": [
    "刑罚",
    "伤害",
    "纠纷",
    "内心痛苦",
    "不顺"
  ],
  "types": {
    "丑戌未": {
      "象": [
        "持势之刑",
        "各恃己力",
        "强势互伤",
        "谁也不服谁",
        "大象打架(草地遭殃)"
      ]
    },
    "寅巳申": {
      "象": [
        "无恩之刑",
        "恩将仇报",
        "翻脸不认人",
        "对人太好反被咬",
        "知恩不报"
      ]
    },
    "子卯": {
      "象": [
        "无礼之刑",
        "以下犯上",
        "尊卑不分",
        "感情伤害",
        "言语无礼"
      ]
    },
    "辰午酉亥": {
      "象": [
        "自刑",
        "自己为难自己",
        "内心痛苦",
        "自我否定",
        "左也不是右也不是"
      ]
    }
  },
  "contexts": {
    "general": {
      "state": [
        "伤害",
        "刑罚",
        "纠纷",
        "痛苦",
        "不顺利",
        "法律问题"
      ]
    },
    "career": {
      "state": [
        "职权纠纷",
        "法律风险",
        "被整",
        "内部争斗"
      ]
    },
    "relationship": {
      "state": [
        "互相伤害",
        "感情折磨",
        "家暴倾向"
      ]
    },
    "health": {
      "state": [
        "受伤",
        "手术",
        "疼痛"
      ]
    }
  }
}